snoozebot/__init__.py
snoozebot-0.0.3.dist-info/COPYING
snoozebot-0.0.3.dist-info/METADATA
snoozebot-0.0.3.dist-info/WHEEL
snoozebot-0.0.3.dist-info/top_level.txt
snoozebot-0.0.3.dist-info/RECORD
