Metadata-Version: 2.1
Name: snoozebot
Version: 0.0.3
Summary: Thread- and battery-friendly time.sleep() replacement
Home-page: https://github.com/BjarniRunar/python-snoozebot
Author: Bjarni R. Einarsson <bre@klaki.net>
Author-email: bre@klaki.net
License: LGPLv3+
Download-URL: https://github.com/BjarniRunar/python-snoozebot/archive/v0.0.1.tar.gz
Keywords: sleep powersaving threads threading
Platform: UNKNOWN
Classifier: Development Status :: 4 - Beta
Classifier: Intended Audience :: Developers
Classifier: License :: OSI Approved :: GNU Lesser General Public License v3 or later (LGPLv3+)
Classifier: Programming Language :: Python
Classifier: Programming Language :: Python :: 3
Classifier: Topic :: Software Development :: Libraries :: Python Modules
